setup.py
apps/__init__.py
apps/config.py
apps/project.py
apps/utils.py
apps/vanguard.py
apps/command/__init__.py
apps/command/add.py
apps/command/base.py
apps/command/config.py
apps/command/generate.py
apps/command/localize.py
apps/command/package.py
apps/command/push.py
apps/command/serve.py
apps/command/setup.py
apps/command/submit.py
apps/command/update.py
apps/data/__init__.py
apps_sdk.egg-info/PKG-INFO
apps_sdk.egg-info/SOURCES.txt
apps_sdk.egg-info/dependency_links.txt
apps_sdk.egg-info/entry_points.txt
apps_sdk.egg-info/requires.txt
apps_sdk.egg-info/top_level.txt