Metadata-Version: 1.0
Name: apps-sdk
Version: 0.2
Summary: Build tool to develop, build and package apps.
Home-page: UNKNOWN
Author: Thomas Rampelberg
Author-email: thomas@bittorrent.com
License: UNKNOWN
Platform: UNKNOWN
